remote_twin_baker/__init__.py
remote_twin_baker/config.yaml
remote_twin_baker/app/__init__.py
remote_twin_baker/app/app_server.py
remote_twin_baker/app/server.py
remote_twin_baker/client/__init__.py
remote_twin_baker/client/remote_execution.py
remote_twin_baker/utils/__init__.py
remote_twin_baker/utils/merge_env_requirements.py
remote_twin_baker/utils/paths.py
remote_twin_baker/utils/util.py
remote_twin_baker-0.1.0.dist-info/METADATA
remote_twin_baker-0.1.0.dist-info/WHEEL
remote_twin_baker-0.1.0.dist-info/licenses/LICENSE
remote_twin_baker-0.1.0.dist-info/RECORD
