Metadata-Version: 2.4
Name: remote-twin-baker
Version: 0.1.0
Summary: A Python package for managing remote environment requirements
Project-URL: Homepage, https://github.com/YankeeMarco/remote-twin-baker
Project-URL: Repository, https://github.com/YankeeMarco/remote-twin-baker.git
Author-email: Your Name <your.email@example.com>
License:                                  Apache License
License-File: LICENSE
Requires-Python: >=3.8
Requires-Dist: flask>=2.0
Requires-Dist: pyyaml>=6.0
Requires-Dist: requests>=2.28.0
